{"statuses": [{"created_at": "Sun Mar 18 07:17:32 +0000 2018", "id": 975269960564973568, "id_str": "975269960564973568", "text": "#TRON's #TRX will be listed on @otcbtc , TRX/BTC, TRX/ETH will be available on 14:00, March 20(GMT+8). $TRX\u2026 https://t.co/1L880TasGl", "truncated": true, "entities": {"hashtags": [{"text": "TRON", "indices": [0, 5]}, {"text": "TRX", "indices": [8, 12]}], "symbols": [{"text": "TRX", "indices": [103, 107]}], "user_mentions": [{"screen_name": "otcbtc", "name": "OTCBTC", "id": 920142242571943936, "id_str": "920142242571943936", "indices": [31, 38]}], "urls": [{"url": "https://t.co/1L880TasGl", "expanded_url": "https://twitter.com/i/web/status/975269960564973568", "display_url": "twitter.com/i/web/status/9\u2026", "indices": [109, 132]}]}, "metadata": {"result_type": "popular", "iso_language_code": "en"}, "source": "<a href=\"http://twitter.com\" rel=\"nofollow\">Twitter Web Client</a>", "in_reply_to_status_id": null, "in_reply_to_status_id_str": null, "in_reply_to_user_id": null, "in_reply_to_user_id_str": null, "in_reply_to_screen_name": null, "user": {"id": 894231710065446912, "id_str": "894231710065446912", "name": "Tron Foundation", "screen_name": "Tronfoundation", "location": "San Francisco, CA", "description": "TRON is a blockchain-based open source global digital entertainment protocol. TRON Official Telegram: https://t.co/rKY1gZ5Y3X", "url": "https://t.co/TjkPRP9h16", "entities": {"url": {"urls": [{"url": "https://t.co/TjkPRP9h16", "expanded_url": "https://tron.network", "display_url": "tron.network", "indices": [0, 23]}]}, "description": {"urls": [{"url": "https://t.co/rKY1gZ5Y3X", "expanded_url": "http://t.me/tronnetworkEN", "display_url": "t.me/tronnetworkEN", "indices": [102, 125]}]}}, "protected": false, "followers_count": 270499, "friends_count": 114, "listed_count": 1546, "created_at": "Sun Aug 06 16:20:28 +0000 2017", "favourites_count": 144, "utc_offset": -25200, "time_zone": "Pacific Time (US & Canada)", "geo_enabled": false, "verified": true, "statuses_count": 351, "lang": "en", "contributors_enabled": false, "is_translator": false, "is_translation_enabled": false, "profile_background_color": "000000", "profile_background_image_url": "http://abs.twimg.com/images/themes/theme1/bg.png", "profile_background_image_url_https": "https://abs.twimg.com/images/themes/theme1/bg.png", "profile_background_tile": false, "profile_image_url": "http://pbs.twimg.com/profile_images/894232987805650949/sCtxN4Wh_normal.jpg", "profile_image_url_https": "https://pbs.twimg.com/profile_images/894232987805650949/sCtxN4Wh_normal.jpg", "profile_banner_url": "https://pbs.twimg.com/profile_banners/894231710065446912/1505024968", "profile_link_color": "ABB8C2", "profile_sidebar_border_color": "000000", "profile_sidebar_fill_color": "000000", "profile_text_color": "000000", "profile_use_background_image": false, "has_extended_profile": true, "default_profile": false, "default_profile_image": false, "following": false, "follow_request_sent": false, "notifications": false, "translator_type": "none"}, "geo": null, "coordinates": null, "place": null, "contributors": null, "is_quote_status": false, "retweet_count": 434, "favorite_count": 1289, "favorited": false, "retweeted": false, "possibly_sensitive": false, "lang": "en"}, {"created_at": "Mon Mar 19 19:46:41 +0000 2018", "id": 975820877487984640, "id_str": "975820877487984640", "text": "The market may have been a bit slow, but it\u2019s catching up to this prediction\u2026 @binarybits writes more in-depth on e\u2026 https://t.co/O3fDwfU9u1", "truncated": true, "entities": {"hashtags": [], "symbols": [], "user_mentions": [{"screen_name": "binarybits", "name": "Timothy B. Lee", "id": 14165170, "id_str": "14165170", "indices": [78, 89]}], "urls": [{"url": "https://t.co/O3fDwfU9u1", "expanded_url": "https://twitter.com/i/web/status/975820877487984640", "display_url": "twitter.com/i/web/status/9\u2026", "indices": [117, 140]}]}, "metadata": {"result_type": "popular", "iso_language_code": "en"}, "source": "<a href=\"http://twitter.com\" rel=\"nofollow\">Twitter Web Client</a>", "in_reply_to_status_id": null, "in_reply_to_status_id_str": null, "in_reply_to_user_id": null, "in_reply_to_user_id_str": null, "in_reply_to_screen_name": null, "user": {"id": 28582680, "id_str": "28582680", "name": "Brad Garlinghouse", "screen_name": "bgarlinghouse", "location": "", "description": "CEO at Ripple", "url": "https://t.co/dnr5DkS7Zf", "entities": {"url": {"urls": [{"url": "https://t.co/dnr5DkS7Zf", "expanded_url": "http://www.ripple.com", "display_url": "ripple.com", "indices": [0, 23]}]}, "description": {"urls": []}}, "protected": false, "followers_count": 174837, "friends_count": 415, "listed_count": 1550, "created_at": "Fri Apr 03 15:16:31 +0000 2009", "favourites_count": 459, "utc_offset": -25200, "time_zone": "Pacific Time (US & Canada)", "geo_enabled": false, "verified": true, "statuses_count": 290, "lang": "en", "contributors_enabled": false, "is_translator": false, "is_translation_enabled": false, "profile_background_color": "F2F2F2", "profile_background_image_url": "http://pbs.twimg.com/profile_background_images/378800000020570345/808cedd0ca83df5a6dcfa89d0ff1a4bc.png", "profile_background_image_url_https": "https://pbs.twimg.com/profile_background_images/378800000020570345/808cedd0ca83df5a6dcfa89d0ff1a4bc.png", "profile_background_tile": true, "profile_image_url": "http://pbs.twimg.com/profile_images/816347848702758913/TWoCdC1L_normal.jpg", "profile_image_url_https": "https://pbs.twimg.com/profile_images/816347848702758913/TWoCdC1L_normal.jpg", "profile_banner_url": "https://pbs.twimg.com/profile_banners/28582680/1512760986", "profile_link_color": "3B94D9", "profile_sidebar_border_color": "FFFFFF", "profile_sidebar_fill_color": "DDEEF6", "profile_text_color": "333333", "profile_use_background_image": true, "has_extended_profile": true, "default_profile": false, "default_profile_image": false, "following": false, "follow_request_sent": false, "notifications": false, "translator_type": "none"}, "geo": null, "coordinates": null, "place": null, "contributors": null, "is_quote_status": true, "quoted_status_id": 971552789229797376, "quoted_status_id_str": "971552789229797376", "quoted_status": {"created_at": "Thu Mar 08 01:06:50 +0000 2018", "id": 971552789229797376, "id_str": "971552789229797376", "text": "My POV on the SEC statement today - the market is having an outsized reaction. Exchanges ultimately have three opti\u2026 https://t.co/mA0I1W7m3c", "truncated": true, "entities": {"hashtags": [], "symbols": [], "user_mentions": [], "urls": [{"url": "https://t.co/mA0I1W7m3c", "expanded_url": "https://twitter.com/i/web/status/971552789229797376", "display_url": "twitter.com/i/web/status/9\u2026", "indices": [117, 140]}]}, "metadata": {"result_type": "popular", "iso_language_code": "en"}, "source": "<a href=\"http://twitter.com\" rel=\"nofollow\">Twitter Web Client</a>", "in_reply_to_status_id": null, "in_reply_to_status_id_str": null, "in_reply_to_user_id": null, "in_reply_to_user_id_str": null, "in_reply_to_screen_name": null, "user": {"id": 28582680, "id_str": "28582680", "name": "Brad Garlinghouse", "screen_name": "bgarlinghouse", "location": "", "description": "CEO at Ripple", "url": "https://t.co/dnr5DkS7Zf", "entities": {"url": {"urls": [{"url": "https://t.co/dnr5DkS7Zf", "expanded_url": "http://www.ripple.com", "display_url": "ripple.com", "indices": [0, 23]}]}, "description": {"urls": []}}, "protected": false, "followers_count": 174837, "friends_count": 415, "listed_count": 1550, "created_at": "Fri Apr 03 15:16:31 +0000 2009", "favourites_count": 459, "utc_offset": -25200, "time_zone": "Pacific Time (US & Canada)", "geo_enabled": false, "verified": true, "statuses_count": 290, "lang": "en", "contributors_enabled": false, "is_translator": false, "is_translation_enabled": false, "profile_background_color": "F2F2F2", "profile_background_image_url": "http://pbs.twimg.com/profile_background_images/378800000020570345/808cedd0ca83df5a6dcfa89d0ff1a4bc.png", "profile_background_image_url_https": "https://pbs.twimg.com/profile_background_images/378800000020570345/808cedd0ca83df5a6dcfa89d0ff1a4bc.png", "profile_background_tile": true, "profile_image_url": "http://pbs.twimg.com/profile_images/816347848702758913/TWoCdC1L_normal.jpg", "profile_image_url_https": "https://pbs.twimg.com/profile_images/816347848702758913/TWoCdC1L_normal.jpg", "profile_banner_url": "https://pbs.twimg.com/profile_banners/28582680/1512760986", "profile_link_color": "3B94D9", "profile_sidebar_border_color": "FFFFFF", "profile_sidebar_fill_color": "DDEEF6", "profile_text_color": "333333", "profile_use_background_image": true, "has_extended_profile": true, "default_profile": false, "default_profile_image": false, "following": false, "follow_request_sent": false, "notifications": false, "translator_type": "none"}, "geo": null, "coordinates": null, "place": null, "contributors": null, "is_quote_status": false, "retweet_count": 758, "favorite_count": 2017, "favorited": false, "retweeted": false, "lang": "en"}, "retweet_count": 93, "favorite_count": 210, "favorited": false, "retweeted": false, "possibly_sensitive": false, "lang": "en"}, {"created_at": "Sun Mar 18 22:33:00 +0000 2018", "id": 975500344104050689, "id_str": "975500344104050689", "text": "The Classic Community is Growing Fast!\n\nWe've Now Suprassed 1K Classic Members!\ud83c\udf89\n\nhttps://t.co/bQ5IYo9SvC \n\n- Annou\u2026 https://t.co/xIz9VdhPgx", "truncated": true, "entities": {"hashtags": [], "symbols": [], "user_mentions": [], "urls": [{"url": "https://t.co/bQ5IYo9SvC", "expanded_url": "http://forum.ethereumclassic.org", "display_url": "forum.ethereumclassic.org", "indices": [82, 105]}, {"url": "https://t.co/xIz9VdhPgx", "expanded_url": "https://twitter.com/i/web/status/975500344104050689", "display_url": "twitter.com/i/web/status/9\u2026", "indices": [117, 140]}]}, "metadata": {"result_type": "popular", "iso_language_code": "en"}, "source": "<a href=\"https://about.twitter.com/products/tweetdeck\" rel=\"nofollow\">TweetDeck</a>", "in_reply_to_status_id": null, "in_reply_to_status_id_str": null, "in_reply_to_user_id": null, "in_reply_to_user_id_str": null, "in_reply_to_screen_name": null, "user": {"id": 759252279862104064, "id_str": "759252279862104064", "name": "Ethereum Classic", "screen_name": "eth_classic", "location": "Blockchain", "description": "Latest News and Information from Ethereum Classic (ETC). A crypto-currency with smart contracts which respects immutability and neutrality.", "url": "https://t.co/rYlDvxioAU", "entities": {"url": {"urls": [{"url": "https://t.co/rYlDvxioAU", "expanded_url": "http://ethereumclassic.org", "display_url": "ethereumclassic.org", "indices": [0, 23]}]}, "description": {"urls": []}}, "protected": false, "followers_count": 194976, "friends_count": 530, "listed_count": 1992, "created_at": "Sat Jul 30 05:00:24 +0000 2016", "favourites_count": 6302, "utc_offset": -39600, "time_zone": "International Date Line West", "geo_enabled": false, "verified": true, "statuses_count": 2464, "lang": "en", "contributors_enabled": false, "is_translator": false, "is_translation_enabled": false, "profile_background_color": "000000", "profile_background_image_url": "http://abs.twimg.com/images/themes/theme1/bg.png", "profile_background_image_url_https": "https://abs.twimg.com/images/themes/theme1/bg.png", "profile_background_tile": false, "profile_image_url": "http://pbs.twimg.com/profile_images/875555509738381313/8o5g6CP1_normal.jpg", "profile_image_url_https": "https://pbs.twimg.com/profile_images/875555509738381313/8o5g6CP1_normal.jpg", "profile_banner_url": "https://pbs.twimg.com/profile_banners/759252279862104064/1471042272", "profile_link_color": "006400", "profile_sidebar_border_color": "000000", "profile_sidebar_fill_color": "000000", "profile_text_color": "000000", "profile_use_background_image": false, "has_extended_profile": true, "default_profile": false, "default_profile_image": false, "following": false, "follow_request_sent": false, "notifications": false, "translator_type": "none"}, "geo": null, "coordinates": null, "place": null, "contributors": null, "is_quote_status": false, "retweet_count": 43, "favorite_count": 99, "favorited": false, "retweeted": false, "possibly_sensitive": false, "lang": "en"}, {"created_at": "Mon Mar 19 03:43:30 +0000 2018", "id": 975578482976567296, "id_str": "975578482976567296", "text": "We are bringing the Founder of Wanchain Jack Lu and President Dustin Byington live via videoconference into Austral\u2026 https://t.co/DCi8xm6mmg", "truncated": true, "entities": {"hashtags": [], "symbols": [], "user_mentions": [], "urls": [{"url": "https://t.co/DCi8xm6mmg", "expanded_url": "https://twitter.com/i/web/status/975578482976567296", "display_url": "twitter.com/i/web/status/9\u2026", "indices": [117, 140]}]}, "metadata": {"result_type": "popular", "iso_language_code": "en"}, "source": "<a href=\"http://twitter.com\" rel=\"nofollow\">Twitter Web Client</a>", "in_reply_to_status_id": null, "in_reply_to_status_id_str": null, "in_reply_to_user_id": null, "in_reply_to_user_id_str": null, "in_reply_to_screen_name": null, "user": {"id": 883984505119297536, "id_str": "883984505119297536", "name": "wanchain", "screen_name": "wanchain_org", "location": "", "description": "Wanchain seeks to create a new distributed financial infrastructure, connecting different blockchain networks together to exchange value.", "url": "https://t.co/opX3dUUtfZ", "entities": {"url": {"urls": [{"url": "https://t.co/opX3dUUtfZ", "expanded_url": "https://www.wanchain.org", "display_url": "wanchain.org", "indices": [0, 23]}]}, "description": {"urls": []}}, "protected": false, "followers_count": 89929, "friends_count": 55, "listed_count": 662, "created_at": "Sun Jul 09 09:41:44 +0000 2017", "favourites_count": 6, "utc_offset": -25200, "time_zone": "Pacific Time (US & Canada)", "geo_enabled": false, "verified": true, "statuses_count": 116, "lang": "en", "contributors_enabled": false, "is_translator": false, "is_translation_enabled": false, "profile_background_color": "F5F8FA", "profile_background_image_url": null, "profile_background_image_url_https": null, "profile_background_tile": false, "profile_image_url": "http://pbs.twimg.com/profile_images/892101551421968385/F5QhRFCS_normal.jpg", "profile_image_url_https": "https://pbs.twimg.com/profile_images/892101551421968385/F5QhRFCS_normal.jpg", "profile_banner_url": "https://pbs.twimg.com/profile_banners/883984505119297536/1517420075", "profile_link_color": "1DA1F2", "profile_sidebar_border_color": "C0DEED", "profile_sidebar_fill_color": "DDEEF6", "profile_text_color": "333333", "profile_use_background_image": true, "has_extended_profile": false, "default_profile": true, "default_profile_image": false, "following": false, "follow_request_sent": false, "notifications": false, "translator_type": "none"}, "geo": null, "coordinates": null, "place": null, "contributors": null, "is_quote_status": false, "retweet_count": 45, "favorite_count": 157, "favorited": false, "retweeted": false, "possibly_sensitive": false, "lang": "en"}, {"created_at": "Mon Mar 19 07:44:21 +0000 2018", "id": 975639095862063104, "id_str": "975639095862063104", "text": "Wanchain Teams Up With Various Austin Companies to Form Regional Blockchain Innovation Hub\n\nhttps://t.co/ykgKKVjwa4\u2026 https://t.co/uCZBMFGq1a", "truncated": true, "entities": {"hashtags": [], "symbols": [], "user_mentions": [], "urls": [{"url": "https://t.co/ykgKKVjwa4", "expanded_url": "https://www.crowdfundinsider.com/2018/02/128591-wanchain-teams-various-austin-companies-form-regional-blockchain-innovation-hub/", "display_url": "crowdfundinsider.com/2018/02/128591\u2026", "indices": [92, 115]}, {"url": "https://t.co/uCZBMFGq1a", "expanded_url": "https://twitter.com/i/web/status/975639095862063104", "display_url": "twitter.com/i/web/status/9\u2026", "indices": [117, 140]}]}, "metadata": {"result_type": "popular", "iso_language_code": "en"}, "source": "<a href=\"http://twitter.com\" rel=\"nofollow\">Twitter Web Client</a>", "in_reply_to_status_id": null, "in_reply_to_status_id_str": null, "in_reply_to_user_id": null, "in_reply_to_user_id_str": null, "in_reply_to_screen_name": null, "user": {"id": 883984505119297536, "id_str": "883984505119297536", "name": "wanchain", "screen_name": "wanchain_org", "location": "", "description": "Wanchain seeks to create a new distributed financial infrastructure, connecting different blockchain networks together to exchange value.", "url": "https://t.co/opX3dUUtfZ", "entities": {"url": {"urls": [{"url": "https://t.co/opX3dUUtfZ", "expanded_url": "https://www.wanchain.org", "display_url": "wanchain.org", "indices": [0, 23]}]}, "description": {"urls": []}}, "protected": false, "followers_count": 89929, "friends_count": 55, "listed_count": 662, "created_at": "Sun Jul 09 09:41:44 +0000 2017", "favourites_count": 6, "utc_offset": -25200, "time_zone": "Pacific Time (US & Canada)", "geo_enabled": false, "verified": true, "statuses_count": 116, "lang": "en", "contributors_enabled": false, "is_translator": false, "is_translation_enabled": false, "profile_background_color": "F5F8FA", "profile_background_image_url": null, "profile_background_image_url_https": null, "profile_background_tile": false, "profile_image_url": "http://pbs.twimg.com/profile_images/892101551421968385/F5QhRFCS_normal.jpg", "profile_image_url_https": "https://pbs.twimg.com/profile_images/892101551421968385/F5QhRFCS_normal.jpg", "profile_banner_url": "https://pbs.twimg.com/profile_banners/883984505119297536/1517420075", "profile_link_color": "1DA1F2", "profile_sidebar_border_color": "C0DEED", "profile_sidebar_fill_color": "DDEEF6", "profile_text_color": "333333", "profile_use_background_image": true, "has_extended_profile": false, "default_profile": true, "default_profile_image": false, "following": false, "follow_request_sent": false, "notifications": false, "translator_type": "none"}, "geo": null, "coordinates": null, "place": null, "contributors": null, "is_quote_status": false, "retweet_count": 40, "favorite_count": 144, "favorited": false, "retweeted": false, "possibly_sensitive": false, "lang": "en"}, {"created_at": "Sun Mar 18 20:33:43 +0000 2018", "id": 975470324668973056, "id_str": "975470324668973056", "text": "Ask and You Will Receive \ud83d\udde3\ufe0f\n\nGive us your feedback, help us improve \n\nWhat features would you like in Mantis - Shar\u2026 https://t.co/cKLAI9upTF", "truncated": true, "entities": {"hashtags": [], "symbols": [], "user_mentions": [], "urls": [{"url": "https://t.co/cKLAI9upTF", "expanded_url": "https://twitter.com/i/web/status/975470324668973056", "display_url": "twitter.com/i/web/status/9\u2026", "indices": [117, 140]}]}, "metadata": {"result_type": "popular", "iso_language_code": "en"}, "source": "<a href=\"https://about.twitter.com/products/tweetdeck\" rel=\"nofollow\">TweetDeck</a>", "in_reply_to_status_id": null, "in_reply_to_status_id_str": null, "in_reply_to_user_id": null, "in_reply_to_user_id_str": null, "in_reply_to_screen_name": null, "user": {"id": 759252279862104064, "id_str": "759252279862104064", "name": "Ethereum Classic", "screen_name": "eth_classic", "location": "Blockchain", "description": "Latest News and Information from Ethereum Classic (ETC). A crypto-currency with smart contracts which respects immutability and neutrality.", "url": "https://t.co/rYlDvxioAU", "entities": {"url": {"urls": [{"url": "https://t.co/rYlDvxioAU", "expanded_url": "http://ethereumclassic.org", "display_url": "ethereumclassic.org", "indices": [0, 23]}]}, "description": {"urls": []}}, "protected": false, "followers_count": 194976, "friends_count": 530, "listed_count": 1992, "created_at": "Sat Jul 30 05:00:24 +0000 2016", "favourites_count": 6302, "utc_offset": -39600, "time_zone": "International Date Line West", "geo_enabled": false, "verified": true, "statuses_count": 2464, "lang": "en", "contributors_enabled": false, "is_translator": false, "is_translation_enabled": false, "profile_background_color": "000000", "profile_background_image_url": "http://abs.twimg.com/images/themes/theme1/bg.png", "profile_background_image_url_https": "https://abs.twimg.com/images/themes/theme1/bg.png", "profile_background_tile": false, "profile_image_url": "http://pbs.twimg.com/profile_images/875555509738381313/8o5g6CP1_normal.jpg", "profile_image_url_https": "https://pbs.twimg.com/profile_images/875555509738381313/8o5g6CP1_normal.jpg", "profile_banner_url": "https://pbs.twimg.com/profile_banners/759252279862104064/1471042272", "profile_link_color": "006400", "profile_sidebar_border_color": "000000", "profile_sidebar_fill_color": "000000", "profile_text_color": "000000", "profile_use_background_image": false, "has_extended_profile": true, "default_profile": false, "default_profile_image": false, "following": false, "follow_request_sent": false, "notifications": false, "translator_type": "none"}, "geo": null, "coordinates": null, "place": null, "contributors": null, "is_quote_status": false, "retweet_count": 30, "favorite_count": 58, "favorited": false, "retweeted": false, "possibly_sensitive": false, "lang": "en"}, {"created_at": "Sun Mar 18 11:20:00 +0000 2018", "id": 975330976929853441, "id_str": "975330976929853441", "text": "Catch Up on Last Week's \"Let's Talk ETC\" Podcast | Episode 32\ud83c\udf99\ufe0f\n\nAnthony Lusardi, newly hired U.S. Director of the\u2026 https://t.co/Fw9TrvEkxu", "truncated": true, "entities": {"hashtags": [], "symbols": [], "user_mentions": [], "urls": [{"url": "https://t.co/Fw9TrvEkxu", "expanded_url": "https://twitter.com/i/web/status/975330976929853441", "display_url": "twitter.com/i/web/status/9\u2026", "indices": [116, 139]}]}, "metadata": {"result_type": "popular", "iso_language_code": "en"}, "source": "<a href=\"https://about.twitter.com/products/tweetdeck\" rel=\"nofollow\">TweetDeck</a>", "in_reply_to_status_id": null, "in_reply_to_status_id_str": null, "in_reply_to_user_id": null, "in_reply_to_user_id_str": null, "in_reply_to_screen_name": null, "user": {"id": 759252279862104064, "id_str": "759252279862104064", "name": "Ethereum Classic", "screen_name": "eth_classic", "location": "Blockchain", "description": "Latest News and Information from Ethereum Classic (ETC). A crypto-currency with smart contracts which respects immutability and neutrality.", "url": "https://t.co/rYlDvxioAU", "entities": {"url": {"urls": [{"url": "https://t.co/rYlDvxioAU", "expanded_url": "http://ethereumclassic.org", "display_url": "ethereumclassic.org", "indices": [0, 23]}]}, "description": {"urls": []}}, "protected": false, "followers_count": 194976, "friends_count": 530, "listed_count": 1992, "created_at": "Sat Jul 30 05:00:24 +0000 2016", "favourites_count": 6302, "utc_offset": -39600, "time_zone": "International Date Line West", "geo_enabled": false, "verified": true, "statuses_count": 2464, "lang": "en", "contributors_enabled": false, "is_translator": false, "is_translation_enabled": false, "profile_background_color": "000000", "profile_background_image_url": "http://abs.twimg.com/images/themes/theme1/bg.png", "profile_background_image_url_https": "https://abs.twimg.com/images/themes/theme1/bg.png", "profile_background_tile": false, "profile_image_url": "http://pbs.twimg.com/profile_images/875555509738381313/8o5g6CP1_normal.jpg", "profile_image_url_https": "https://pbs.twimg.com/profile_images/875555509738381313/8o5g6CP1_normal.jpg", "profile_banner_url": "https://pbs.twimg.com/profile_banners/759252279862104064/1471042272", "profile_link_color": "006400", "profile_sidebar_border_color": "000000", "profile_sidebar_fill_color": "000000", "profile_text_color": "000000", "profile_use_background_image": false, "has_extended_profile": true, "default_profile": false, "default_profile_image": false, "following": false, "follow_request_sent": false, "notifications": false, "translator_type": "none"}, "geo": null, "coordinates": null, "place": null, "contributors": null, "is_quote_status": false, "retweet_count": 21, "favorite_count": 72, "favorited": false, "retweeted": false, "possibly_sensitive": false, "lang": "en"}, {"created_at": "Sun Mar 18 08:11:00 +0000 2018", "id": 975283413665038337, "id_str": "975283413665038337", "text": "Today's ETC Network Stats \ud83d\udcca $1.5Bln Market Cap - 38K Transactions - $169Mln Trade Vol\n\n#ETCStats #EthereumClassic\u2026 https://t.co/nk4onMcLjl", "truncated": true, "entities": {"hashtags": [{"text": "ETCStats", "indices": [87, 96]}, {"text": "EthereumClassic", "indices": [97, 113]}], "symbols": [], "user_mentions": [], "urls": [{"url": "https://t.co/nk4onMcLjl", "expanded_url": "https://twitter.com/i/web/status/975283413665038337", "display_url": "twitter.com/i/web/status/9\u2026", "indices": [115, 138]}]}, "metadata": {"result_type": "popular", "iso_language_code": "en"}, "source": "<a href=\"https://about.twitter.com/products/tweetdeck\" rel=\"nofollow\">TweetDeck</a>", "in_reply_to_status_id": null, "in_reply_to_status_id_str": null, "in_reply_to_user_id": null, "in_reply_to_user_id_str": null, "in_reply_to_screen_name": null, "user": {"id": 759252279862104064, "id_str": "759252279862104064", "name": "Ethereum Classic", "screen_name": "eth_classic", "location": "Blockchain", "description": "Latest News and Information from Ethereum Classic (ETC). A crypto-currency with smart contracts which respects immutability and neutrality.", "url": "https://t.co/rYlDvxioAU", "entities": {"url": {"urls": [{"url": "https://t.co/rYlDvxioAU", "expanded_url": "http://ethereumclassic.org", "display_url": "ethereumclassic.org", "indices": [0, 23]}]}, "description": {"urls": []}}, "protected": false, "followers_count": 194976, "friends_count": 530, "listed_count": 1992, "created_at": "Sat Jul 30 05:00:24 +0000 2016", "favourites_count": 6302, "utc_offset": -39600, "time_zone": "International Date Line West", "geo_enabled": false, "verified": true, "statuses_count": 2464, "lang": "en", "contributors_enabled": false, "is_translator": false, "is_translation_enabled": false, "profile_background_color": "000000", "profile_background_image_url": "http://abs.twimg.com/images/themes/theme1/bg.png", "profile_background_image_url_https": "https://abs.twimg.com/images/themes/theme1/bg.png", "profile_background_tile": false, "profile_image_url": "http://pbs.twimg.com/profile_images/875555509738381313/8o5g6CP1_normal.jpg", "profile_image_url_https": "https://pbs.twimg.com/profile_images/875555509738381313/8o5g6CP1_normal.jpg", "profile_banner_url": "https://pbs.twimg.com/profile_banners/759252279862104064/1471042272", "profile_link_color": "006400", "profile_sidebar_border_color": "000000", "profile_sidebar_fill_color": "000000", "profile_text_color": "000000", "profile_use_background_image": false, "has_extended_profile": true, "default_profile": false, "default_profile_image": false, "following": false, "follow_request_sent": false, "notifications": false, "translator_type": "none"}, "geo": null, "coordinates": null, "place": null, "contributors": null, "is_quote_status": false, "retweet_count": 30, "favorite_count": 100, "favorited": false, "retweeted": false, "possibly_sensitive": false, "lang": "en"}, {"created_at": "Mon Mar 19 13:28:49 +0000 2018", "id": 975725783972016128, "id_str": "975725783972016128", "text": "Bitcoin, Ethereum and Litecoin trying to recover from the crypto crash over the weekend $BTC $ETH $BCH $LTC https://t.co/a4rTG7oNjf", "truncated": false, "entities": {"hashtags": [], "symbols": [{"text": "BTC", "indices": [88, 92]}, {"text": "ETH", "indices": [93, 97]}, {"text": "BCH", "indices": [98, 102]}, {"text": "LTC", "indices": [103, 107]}], "user_mentions": [], "urls": [], "media": [{"id": 975725381062832128, "id_str": "975725381062832128", "indices": [108, 131], "media_url": "http://pbs.twimg.com/media/DYp5EICVMAAGcUR.jpg", "media_url_https": "https://pbs.twimg.com/media/DYp5EICVMAAGcUR.jpg", "url": "https://t.co/a4rTG7oNjf", "display_url": "pic.twitter.com/a4rTG7oNjf", "expanded_url": "https://twitter.com/CNBCFastMoney/status/975725783972016128/photo/1", "type": "photo", "sizes": {"thumb": {"w": 150, "h": 150, "resize": "crop"}, "small": {"w": 267, "h": 209, "resize": "fit"}, "large": {"w": 267, "h": 209, "resize": "fit"}, "medium": {"w": 267, "h": 209, "resize": "fit"}}}]}, "extended_entities": {"media": [{"id": 975725381062832128, "id_str": "975725381062832128", "indices": [108, 131], "media_url": "http://pbs.twimg.com/media/DYp5EICVMAAGcUR.jpg", "media_url_https": "https://pbs.twimg.com/media/DYp5EICVMAAGcUR.jpg", "url": "https://t.co/a4rTG7oNjf", "display_url": "pic.twitter.com/a4rTG7oNjf", "expanded_url": "https://twitter.com/CNBCFastMoney/status/975725783972016128/photo/1", "type": "photo", "sizes": {"thumb": {"w": 150, "h": 150, "resize": "crop"}, "small": {"w": 267, "h": 209, "resize": "fit"}, "large": {"w": 267, "h": 209, "resize": "fit"}, "medium": {"w": 267, "h": 209, "resize": "fit"}}}]}, "metadata": {"result_type": "popular", "iso_language_code": "en"}, "source": "<a href=\"https://about.twitter.com/products/tweetdeck\" rel=\"nofollow\">TweetDeck</a>", "in_reply_to_status_id": null, "in_reply_to_status_id_str": null, "in_reply_to_user_id": null, "in_reply_to_user_id_str": null, "in_reply_to_screen_name": null, "user": {"id": 16732770, "id_str": "16732770", "name": "CNBC's Fast Money", "screen_name": "CNBCFastMoney", "location": "NASDAQ", "description": "Fast Money with @MelissaLeeCNBC airs weeknights at 5P ET, only on @CNBC. America's post-market show.", "url": "https://t.co/g476qiApSd", "entities": {"url": {"urls": [{"url": "https://t.co/g476qiApSd", "expanded_url": "http://fastmoney.cnbc.com", "display_url": "fastmoney.cnbc.com", "indices": [0, 23]}]}, "description": {"urls": []}}, "protected": false, "followers_count": 227534, "friends_count": 1232, "listed_count": 3287, "created_at": "Tue Oct 14 03:16:30 +0000 2008", "favourites_count": 2256, "utc_offset": -14400, "time_zone": "Eastern Time (US & Canada)", "geo_enabled": true, "verified": true, "statuses_count": 41897, "lang": "en", "contributors_enabled": false, "is_translator": false, "is_translation_enabled": false, "profile_background_color": "0D181F", "profile_background_image_url": "http://pbs.twimg.com/profile_background_images/378800000008568647/b8238ba4b7b9547254d954a2876d44d3.png", "profile_background_image_url_https": "https://pbs.twimg.com/profile_background_images/378800000008568647/b8238ba4b7b9547254d954a2876d44d3.png", "profile_background_tile": false, "profile_image_url": "http://pbs.twimg.com/profile_images/819679248956977153/GTAbjy_O_normal.jpg", "profile_image_url_https": "https://pbs.twimg.com/profile_images/819679248956977153/GTAbjy_O_normal.jpg", "profile_banner_url": "https://pbs.twimg.com/profile_banners/16732770/1481922975", "profile_link_color": "727722", "profile_sidebar_border_color": "FFFFFF", "profile_sidebar_fill_color": "BEBFBA", "profile_text_color": "333333", "profile_use_background_image": true, "has_extended_profile": false, "default_profile": false, "default_profile_image": false, "following": false, "follow_request_sent": false, "notifications": false, "translator_type": "none"}, "geo": null, "coordinates": null, "place": null, "contributors": null, "is_quote_status": false, "retweet_count": 16, "favorite_count": 51, "favorited": false, "retweeted": false, "possibly_sensitive": false, "lang": "en"}, {"created_at": "Tue Mar 13 13:29:10 +0000 2018", "id": 973551543483011072, "id_str": "973551543483011072", "text": "Excellent work, etherchain!\n\nhttps://t.co/doAqk8HbAq\n\n(Anyone replying to this claiming to be giving away ETH is a scammer, as usual)", "truncated": false, "entities": {"hashtags": [], "symbols": [], "user_mentions": [], "urls": [{"url": "https://t.co/doAqk8HbAq", "expanded_url": "https://www.etherchain.org/correlations", "display_url": "etherchain.org/correlations", "indices": [29, 52]}]}, "metadata": {"result_type": "popular", "iso_language_code": "en"}, "source": "<a href=\"http://twitter.com\" rel=\"nofollow\">Twitter Web Client</a>", "in_reply_to_status_id": null, "in_reply_to_status_id_str": null, "in_reply_to_user_id": null, "in_reply_to_user_id_str": null, "in_reply_to_screen_name": null, "user": {"id": 295218901, "id_str": "295218901", "name": "Vitalik \"Not giving away ETH\" Buterin", "screen_name": "VitalikButerin", "location": "Earth", "description": "See https://t.co/iBNSW4KCSO", "url": "http://t.co/yDFD4r4WXU", "entities": {"url": {"urls": [{"url": "http://t.co/yDFD4r4WXU", "expanded_url": "http://vitalik.ca", "display_url": "vitalik.ca", "indices": [0, 22]}]}, "description": {"urls": [{"url": "https://t.co/iBNSW4KCSO", "expanded_url": "https://about.me/vitalik_buterin", "display_url": "about.me/vitalik_buterin", "indices": [4, 27]}]}}, "protected": false, "followers_count": 703336, "friends_count": 161, "listed_count": 8160, "created_at": "Sun May 08 16:03:03 +0000 2011", "favourites_count": 2722, "utc_offset": null, "time_zone": null, "geo_enabled": false, "verified": true, "statuses_count": 5933, "lang": "en", "contributors_enabled": false, "is_translator": false, "is_translation_enabled": false, "profile_background_color": "C0DEED", "profile_background_image_url": "http://abs.twimg.com/images/themes/theme1/bg.png", "profile_background_image_url_https": "https://abs.twimg.com/images/themes/theme1/bg.png", "profile_background_tile": false, "profile_image_url": "http://pbs.twimg.com/profile_images/965149731541344257/h6nqzAAq_normal.jpg", "profile_image_url_https": "https://pbs.twimg.com/profile_images/965149731541344257/h6nqzAAq_normal.jpg", "profile_banner_url": "https://pbs.twimg.com/profile_banners/295218901/1469015022", "profile_link_color": "1DA1F2", "profile_sidebar_border_color": "C0DEED", "profile_sidebar_fill_color": "DDEEF6", "profile_text_color": "333333", "profile_use_background_image": true, "has_extended_profile": true, "default_profile": true, "default_profile_image": false, "following": false, "follow_request_sent": false, "notifications": false, "translator_type": "none"}, "geo": null, "coordinates": null, "place": null, "contributors": null, "is_quote_status": false, "retweet_count": 194, "favorite_count": 874, "favorited": false, "retweeted": false, "possibly_sensitive": false, "lang": "en"}, {"created_at": "Mon Mar 19 09:41:33 +0000 2018", "id": 975668590501392384, "id_str": "975668590501392384", "text": "Crypto update:\n#BITCOIN  8224.17  -3.48%\n#ETHER  532.13  -13.15%\n#BITCOINCASH  925.72  -9.07%\n#RIPPLE  0.649  -6.35\u2026 https://t.co/zhhFJ5qweE", "truncated": true, "entities": {"hashtags": [{"text": "BITCOIN", "indices": [15, 23]}, {"text": "ETHER", "indices": [41, 47]}, {"text": "BITCOINCASH", "indices": [65, 77]}, {"text": "RIPPLE", "indices": [94, 101]}], "symbols": [], "user_mentions": [], "urls": [{"url": "https://t.co/zhhFJ5qweE", "expanded_url": "https://twitter.com/i/web/status/975668590501392384", "display_url": "twitter.com/i/web/status/9\u2026", "indices": [117, 140]}]}, "metadata": {"result_type": "popular", "iso_language_code": "en"}, "source": "<a href=\"https://about.twitter.com/products/tweetdeck\" rel=\"nofollow\">TweetDeck</a>", "in_reply_to_status_id": null, "in_reply_to_status_id_str": null, "in_reply_to_user_id": null, "in_reply_to_user_id_str": null, "in_reply_to_screen_name": null, "user": {"id": 1533387092, "id_str": "1533387092", "name": "IGSquawk", "screen_name": "IGSquawk", "location": "Global", "description": "Live from our trading floor, IG dealers share news and client sentiment 24 hours a day. Tweets are not investment advice, losses can exceed initial deposits.", "url": "https://t.co/sI0u2wlYh2", "entities": {"url": {"urls": [{"url": "https://t.co/sI0u2wlYh2", "expanded_url": "https://www.ig.com", "display_url": "ig.com", "indices": [0, 23]}]}, "description": {"urls": []}}, "protected": false, "followers_count": 17178, "friends_count": 586, "listed_count": 614, "created_at": "Thu Jun 20 09:14:25 +0000 2013", "favourites_count": 234, "utc_offset": 0, "time_zone": "London", "geo_enabled": true, "verified": true, "statuses_count": 15351, "lang": "en", "contributors_enabled": false, "is_translator": false, "is_translation_enabled": false, "profile_background_color": "C0DEED", "profile_background_image_url": "http://pbs.twimg.com/profile_background_images/578879462785163264/cNrtOFRF.jpeg", "profile_background_image_url_https": "https://pbs.twimg.com/profile_background_images/578879462785163264/cNrtOFRF.jpeg", "profile_background_tile": false, "profile_image_url": "http://pbs.twimg.com/profile_images/915550756236906496/BDC9Kf8x_normal.jpg", "profile_image_url_https": "https://pbs.twimg.com/profile_images/915550756236906496/BDC9Kf8x_normal.jpg", "profile_banner_url": "https://pbs.twimg.com/profile_banners/1533387092/1402495795", "profile_link_color": "FA1919", "profile_sidebar_border_color": "FFFFFF", "profile_sidebar_fill_color": "DDEEF6", "profile_text_color": "333333", "profile_use_background_image": true, "has_extended_profile": false, "default_profile": false, "default_profile_image": false, "following": false, "follow_request_sent": false, "notifications": false, "translator_type": "none"}, "geo": null, "coordinates": null, "place": null, "contributors": null, "is_quote_status": false, "retweet_count": 6, "favorite_count": 3, "favorited": false, "retweeted": false, "lang": "en"}, {"created_at": "Mon Mar 19 12:25:14 +0000 2018", "id": 975709781062189056, "id_str": "975709781062189056", "text": "Crypto update:\n#BITCOIN  8298.60  -2.61%\n#ETHER  530.13  -13.48%\n#BITCOINCASH  946.95  -6.98%\n#RIPPLE  0.648  -6.51\u2026 https://t.co/JvX3EGKF7q", "truncated": true, "entities": {"hashtags": [{"text": "BITCOIN", "indices": [15, 23]}, {"text": "ETHER", "indices": [41, 47]}, {"text": "BITCOINCASH", "indices": [65, 77]}, {"text": "RIPPLE", "indices": [94, 101]}], "symbols": [], "user_mentions": [], "urls": [{"url": "https://t.co/JvX3EGKF7q", "expanded_url": "https://twitter.com/i/web/status/975709781062189056", "display_url": "twitter.com/i/web/status/9\u2026", "indices": [117, 140]}]}, "metadata": {"result_type": "popular", "iso_language_code": "en"}, "source": "<a href=\"https://about.twitter.com/products/tweetdeck\" rel=\"nofollow\">TweetDeck</a>", "in_reply_to_status_id": null, "in_reply_to_status_id_str": null, "in_reply_to_user_id": null, "in_reply_to_user_id_str": null, "in_reply_to_screen_name": null, "user": {"id": 1533387092, "id_str": "1533387092", "name": "IGSquawk", "screen_name": "IGSquawk", "location": "Global", "description": "Live from our trading floor, IG dealers share news and client sentiment 24 hours a day. Tweets are not investment advice, losses can exceed initial deposits.", "url": "https://t.co/sI0u2wlYh2", "entities": {"url": {"urls": [{"url": "https://t.co/sI0u2wlYh2", "expanded_url": "https://www.ig.com", "display_url": "ig.com", "indices": [0, 23]}]}, "description": {"urls": []}}, "protected": false, "followers_count": 17178, "friends_count": 586, "listed_count": 614, "created_at": "Thu Jun 20 09:14:25 +0000 2013", "favourites_count": 234, "utc_offset": 0, "time_zone": "London", "geo_enabled": true, "verified": true, "statuses_count": 15351, "lang": "en", "contributors_enabled": false, "is_translator": false, "is_translation_enabled": false, "profile_background_color": "C0DEED", "profile_background_image_url": "http://pbs.twimg.com/profile_background_images/578879462785163264/cNrtOFRF.jpeg", "profile_background_image_url_https": "https://pbs.twimg.com/profile_background_images/578879462785163264/cNrtOFRF.jpeg", "profile_background_tile": false, "profile_image_url": "http://pbs.twimg.com/profile_images/915550756236906496/BDC9Kf8x_normal.jpg", "profile_image_url_https": "https://pbs.twimg.com/profile_images/915550756236906496/BDC9Kf8x_normal.jpg", "profile_banner_url": "https://pbs.twimg.com/profile_banners/1533387092/1402495795", "profile_link_color": "FA1919", "profile_sidebar_border_color": "FFFFFF", "profile_sidebar_fill_color": "DDEEF6", "profile_text_color": "333333", "profile_use_background_image": true, "has_extended_profile": false, "default_profile": false, "default_profile_image": false, "following": false, "follow_request_sent": false, "notifications": false, "translator_type": "none"}, "geo": null, "coordinates": null, "place": null, "contributors": null, "is_quote_status": false, "retweet_count": 4, "favorite_count": 3, "favorited": false, "retweeted": false, "lang": "en"}, {"created_at": "Fri Mar 16 07:12:00 +0000 2018", "id": 974543789837770752, "id_str": "974543789837770752", "text": "Circle's Coinbase-Like App Moves ETC Ahead\n\nNow go from cash to $ETC and back with @CircleInvest \n\n#EthereumClassic\u2026 https://t.co/H9KNgdGwdO", "truncated": true, "entities": {"hashtags": [{"text": "EthereumClassic", "indices": [99, 115]}], "symbols": [{"text": "ETC", "indices": [64, 68]}], "user_mentions": [{"screen_name": "circleinvest", "name": "Circle Invest", "id": 845718344225370112, "id_str": "845718344225370112", "indices": [83, 96]}], "urls": [{"url": "https://t.co/H9KNgdGwdO", "expanded_url": "https://twitter.com/i/web/status/974543789837770752", "display_url": "twitter.com/i/web/status/9\u2026", "indices": [117, 140]}]}, "metadata": {"result_type": "popular", "iso_language_code": "en"}, "source": "<a href=\"https://about.twitter.com/products/tweetdeck\" rel=\"nofollow\">TweetDeck</a>", "in_reply_to_status_id": null, "in_reply_to_status_id_str": null, "in_reply_to_user_id": null, "in_reply_to_user_id_str": null, "in_reply_to_screen_name": null, "user": {"id": 759252279862104064, "id_str": "759252279862104064", "name": "Ethereum Classic", "screen_name": "eth_classic", "location": "Blockchain", "description": "Latest News and Information from Ethereum Classic (ETC). A crypto-currency with smart contracts which respects immutability and neutrality.", "url": "https://t.co/rYlDvxioAU", "entities": {"url": {"urls": [{"url": "https://t.co/rYlDvxioAU", "expanded_url": "http://ethereumclassic.org", "display_url": "ethereumclassic.org", "indices": [0, 23]}]}, "description": {"urls": []}}, "protected": false, "followers_count": 194976, "friends_count": 530, "listed_count": 1992, "created_at": "Sat Jul 30 05:00:24 +0000 2016", "favourites_count": 6302, "utc_offset": -39600, "time_zone": "International Date Line West", "geo_enabled": false, "verified": true, "statuses_count": 2464, "lang": "en", "contributors_enabled": false, "is_translator": false, "is_translation_enabled": false, "profile_background_color": "000000", "profile_background_image_url": "http://abs.twimg.com/images/themes/theme1/bg.png", "profile_background_image_url_https": "https://abs.twimg.com/images/themes/theme1/bg.png", "profile_background_tile": false, "profile_image_url": "http://pbs.twimg.com/profile_images/875555509738381313/8o5g6CP1_normal.jpg", "profile_image_url_https": "https://pbs.twimg.com/profile_images/875555509738381313/8o5g6CP1_normal.jpg", "profile_banner_url": "https://pbs.twimg.com/profile_banners/759252279862104064/1471042272", "profile_link_color": "006400", "profile_sidebar_border_color": "000000", "profile_sidebar_fill_color": "000000", "profile_text_color": "000000", "profile_use_background_image": false, "has_extended_profile": true, "default_profile": false, "default_profile_image": false, "following": false, "follow_request_sent": false, "notifications": false, "translator_type": "none"}, "geo": null, "coordinates": null, "place": null, "contributors": null, "is_quote_status": false, "retweet_count": 77, "favorite_count": 217, "favorited": false, "retweeted": false, "possibly_sensitive": false, "lang": "en"}, {"created_at": "Sat Mar 10 20:12:00 +0000 2018", "id": 972565756729753606, "id_str": "972565756729753606", "text": "\u201cNew features in Ethereum Classic, but Still a Drop?\u201d\n\nan outside look at $ETC developments via AllCryptoNews\u2026 https://t.co/IjR4ZdBOHf", "truncated": true, "entities": {"hashtags": [], "symbols": [{"text": "ETC", "indices": [74, 78]}], "user_mentions": [], "urls": [{"url": "https://t.co/IjR4ZdBOHf", "expanded_url": "https://twitter.com/i/web/status/972565756729753606", "display_url": "twitter.com/i/web/status/9\u2026", "indices": [111, 134]}]}, "metadata": {"result_type": "popular", "iso_language_code": "en"}, "source": "<a href=\"https://about.twitter.com/products/tweetdeck\" rel=\"nofollow\">TweetDeck</a>", "in_reply_to_status_id": null, "in_reply_to_status_id_str": null, "in_reply_to_user_id": null, "in_reply_to_user_id_str": null, "in_reply_to_screen_name": null, "user": {"id": 759252279862104064, "id_str": "759252279862104064", "name": "Ethereum Classic", "screen_name": "eth_classic", "location": "Blockchain", "description": "Latest News and Information from Ethereum Classic (ETC). A crypto-currency with smart contracts which respects immutability and neutrality.", "url": "https://t.co/rYlDvxioAU", "entities": {"url": {"urls": [{"url": "https://t.co/rYlDvxioAU", "expanded_url": "http://ethereumclassic.org", "display_url": "ethereumclassic.org", "indices": [0, 23]}]}, "description": {"urls": []}}, "protected": false, "followers_count": 194976, "friends_count": 530, "listed_count": 1992, "created_at": "Sat Jul 30 05:00:24 +0000 2016", "favourites_count": 6302, "utc_offset": -39600, "time_zone": "International Date Line West", "geo_enabled": false, "verified": true, "statuses_count": 2464, "lang": "en", "contributors_enabled": false, "is_translator": false, "is_translation_enabled": false, "profile_background_color": "000000", "profile_background_image_url": "http://abs.twimg.com/images/themes/theme1/bg.png", "profile_background_image_url_https": "https://abs.twimg.com/images/themes/theme1/bg.png", "profile_background_tile": false, "profile_image_url": "http://pbs.twimg.com/profile_images/875555509738381313/8o5g6CP1_normal.jpg", "profile_image_url_https": "https://pbs.twimg.com/profile_images/875555509738381313/8o5g6CP1_normal.jpg", "profile_banner_url": "https://pbs.twimg.com/profile_banners/759252279862104064/1471042272", "profile_link_color": "006400", "profile_sidebar_border_color": "000000", "profile_sidebar_fill_color": "000000", "profile_text_color": "000000", "profile_use_background_image": false, "has_extended_profile": true, "default_profile": false, "default_profile_image": false, "following": false, "follow_request_sent": false, "notifications": false, "translator_type": "none"}, "geo": null, "coordinates": null, "place": null, "contributors": null, "is_quote_status": false, "retweet_count": 84, "favorite_count": 132, "favorited": false, "retweeted": false, "possibly_sensitive": false, "lang": "en"}, {"created_at": "Sat Mar 17 14:00:03 +0000 2018", "id": 975008867762561024, "id_str": "975008867762561024", "text": "How Deploy Your First Contract\ud83d\udccb\n\nA brief &amp; clear guide to deploying a simple smart contract on ETC\n\nCheck out our c\u2026 https://t.co/iDLqch0gKJ", "truncated": true, "entities": {"hashtags": [], "symbols": [], "user_mentions": [], "urls": [{"url": "https://t.co/iDLqch0gKJ", "expanded_url": "https://twitter.com/i/web/status/975008867762561024", "display_url": "twitter.com/i/web/status/9\u2026", "indices": [121, 144]}]}, "metadata": {"result_type": "popular", "iso_language_code": "en"}, "source": "<a href=\"https://about.twitter.com/products/tweetdeck\" rel=\"nofollow\">TweetDeck</a>", "in_reply_to_status_id": null, "in_reply_to_status_id_str": null, "in_reply_to_user_id": null, "in_reply_to_user_id_str": null, "in_reply_to_screen_name": null, "user": {"id": 759252279862104064, "id_str": "759252279862104064", "name": "Ethereum Classic", "screen_name": "eth_classic", "location": "Blockchain", "description": "Latest News and Information from Ethereum Classic (ETC). A crypto-currency with smart contracts which respects immutability and neutrality.", "url": "https://t.co/rYlDvxioAU", "entities": {"url": {"urls": [{"url": "https://t.co/rYlDvxioAU", "expanded_url": "http://ethereumclassic.org", "display_url": "ethereumclassic.org", "indices": [0, 23]}]}, "description": {"urls": []}}, "protected": false, "followers_count": 194976, "friends_count": 530, "listed_count": 1992, "created_at": "Sat Jul 30 05:00:24 +0000 2016", "favourites_count": 6302, "utc_offset": -39600, "time_zone": "International Date Line West", "geo_enabled": false, "verified": true, "statuses_count": 2464, "lang": "en", "contributors_enabled": false, "is_translator": false, "is_translation_enabled": false, "profile_background_color": "000000", "profile_background_image_url": "http://abs.twimg.com/images/themes/theme1/bg.png", "profile_background_image_url_https": "https://abs.twimg.com/images/themes/theme1/bg.png", "profile_background_tile": false, "profile_image_url": "http://pbs.twimg.com/profile_images/875555509738381313/8o5g6CP1_normal.jpg", "profile_image_url_https": "https://pbs.twimg.com/profile_images/875555509738381313/8o5g6CP1_normal.jpg", "profile_banner_url": "https://pbs.twimg.com/profile_banners/759252279862104064/1471042272", "profile_link_color": "006400", "profile_sidebar_border_color": "000000", "profile_sidebar_fill_color": "000000", "profile_text_color": "000000", "profile_use_background_image": false, "has_extended_profile": true, "default_profile": false, "default_profile_image": false, "following": false, "follow_request_sent": false, "notifications": false, "translator_type": "none"}, "geo": null, "coordinates": null, "place": null, "contributors": null, "is_quote_status": false, "retweet_count": 45, "favorite_count": 92, "favorited": false, "retweeted": false, "possibly_sensitive": false, "lang": "en"}], "search_metadata": {"completed_in": 0.058, "max_id": 0, "max_id_str": "0", "query": "ETH", "count": 100, "since_id": 0, "since_id_str": "0"}}